README.rst
setup.cfg
setup.py
typeconverter.py
TypeConverter.egg-info/PKG-INFO
TypeConverter.egg-info/SOURCES.txt
TypeConverter.egg-info/dependency_links.txt
TypeConverter.egg-info/top_level.txt