Metadata-Version: 1.0
Name: TypeConverter
Version: 0.1.1
Summary: Simple type converter
Home-page: https://github.com/hardtack/typeconverter
Author: Geonu Choi
Author-email: 6566gun@gmail.com
License: MIT License
Platform: UNKNOWN
